badook_airflow/__init__.py
badook_airflow/hooks/__init__.py
badook_airflow/hooks/badook_hook.py
badook_airflow/hooks/config/custom-environment-variables.yml
badook_airflow/hooks/config/default.yml
badook_airflow/operators/__init__.py
badook_airflow/operators/badook_operator.py
badook_airflow-0.2.0rc0.dist-info/LICENSE
badook_airflow-0.2.0rc0.dist-info/WHEEL
badook_airflow-0.2.0rc0.dist-info/METADATA
badook_airflow-0.2.0rc0.dist-info/RECORD
