Metadata-Version: 2.1
Name: badook-airflow
Version: 0.2.0rc0
Summary: Apache Airflow integration for badook tests
Home-page: https://github.com/badook-ai/badook-airflow
License: Apache 2
Author: badook engineering
Author-email: engineering@badook.ai
Requires-Python: >=3.9.0,<3.10.0
Classifier: License :: Other/Proprietary License
Classifier: Programming Language :: Python :: 3
Classifier: Programming Language :: Python :: 3.9
Requires-Dist: apache-airflow (>=2.1.2,<3.0.0)
Requires-Dist: badook-tests
Requires-Dist: cached-property (>=1.5.2,<2.0.0)
Requires-Dist: log-symbols (>=0.0.14,<0.0.15)
Requires-Dist: spinners (>=0.0.24,<0.0.25)
Project-URL: Repository, https://github.com/badook-ai/badook-airflow
